[
  {
    "country": "FR",
    "default": true,
    "unit": "kms",
    "active": true,
    "action": "Trottinette",
    "source": "https://base-empreinte.ademe.fr/donnees/jeu-donnees",
    "category": "Trajets",
    "option": "Électrique",
    "amortization": 0,
    "hint": "Indiquez la distance parcourue.",
    "co2e": 25
  },
  {
    "co2e": 679,
    "country": "FR",
    "action": "Principal",
    "active": true,
    "category": "Repas",
    "option": "Poisson"
  },
  {
    "country": "FR",
    "co2e": 144,
    "active": true,
    "action": "Electricité",
    "category": "Logement",
    "option": "Bioéthanol",
    "amortization": 1,
    "hint": "Indiquez votre consommation annuelle en kilowattheure indiquée sur votre facture annuelle d'électricité.",
    "unit": "kWh"
  },
  {
    "country": "FR",
    "co2e": 500000,
    "default": true,
    "action": "Télévision",
    "active": true,
    "category": "Numérique",
    "option": "49 pouces",
    "amortization": 10,
    "hint": "Indiquez le nombre de télévisions 30-40 pouces en votre possession. Il s'agit de télévision dont la diagonale est supérieur à 1 mètre 25 (écran de grande taille)."
  },
  {
    "country": "FR",
    "co2e": 6.4,
    "default": true,
    "action": "Opérateur mobile",
    "active": true,
    "option": "Free",
    "amortization": 0,
    "category": "Services"
  },
  {
    "country": "FR",
    "unit": "kms",
    "active": true,
    "action": "Train",
    "source": "https://medias.sncf.com/sncfcom/pdf/DESTE/Methodologie-generale-InfoGES_2022.pdf",
    "category": "Trajets",
    "option": "Eurostar",
    "amortization": 0,
    "hint": "Indiquez la distance parcourue.",
    "co2e": 7
  },
  {
    "co2e": 512,
    "country": "FR",
    "action": "Boissons",
    "active": true,
    "category": "Repas",
    "option": "Alcool"
  },
  {
    "country": "FR",
    "co2e": 41000,
    "default": true,
    "action": "Manteau",
    "active": true,
    "source": "https://impactco2.fr/habillement/vesteimpermeable",
    "category": "Habits",
    "option": "Veste imperméable ",
    "amortization": 3,
    "hint": "Indiquez le nombre de vestes imperméables en votre possession."
  },
  {
    "country": "FR",
    "co2e": 360,
    "unit": "paquets",
    "default": true,
    "action": "Cigarettes",
    "active": true,
    "category": "Objets",
    "option": "Toutes marques",
    "hint": "Indiquez le nombre de paquets de cigarettes, toutes marques confondues consommés par an.",
    "amortization": 1
  },
  {
    "country": "FR",
    "co2e": 90000,
    "action": "Manteau",
    "active": true,
    "source": "https://impactco2.fr/habillement/manteau",
    "category": "Habits",
    "option": "Manteau d'hiver",
    "amortization": 3,
    "hint": "Indiquez le nombre de manteaux d'hivers en votre prossession."
  },
  {
    "country": "FR",
    "co2e": 31000,
    "action": "Pull",
    "active": true,
    "source": "https://impactco2.fr/habillement",
    "category": "Habits",
    "option": "Sweat en coton",
    "amortization": 2,
    "hint": "Indiquez le nombre de pulls en coton en votre prossession."
  },
  {
    "country": "FR",
    "unit": "heures",
    "comments": "Bateau automoteur/400 à 649 TPL, ADEME",
    "active": true,
    "action": "Bateau",
    "source": "https://base-empreinte.ademe.fr/donnees/jeu-donnees",
    "category": "Trajets",
    "option": "Péniche",
    "amortization": 0,
    "hint": "Indiquez le nombre d'heures d'utilisation.",
    "co2e": 36
  },
  {
    "country": "FR",
    "co2e": 28000,
    "action": "Pull",
    "active": true,
    "source": "https://impactco2.fr/habillement",
    "category": "Habits",
    "option": "Acrylique ",
    "amortization": 2,
    "hint": "Indiquez le nombre de pulls acrylique en votre possession."
  },
  {
    "co2e": 151,
    "country": "FR",
    "action": "Dessert",
    "active": true,
    "category": "Repas",
    "option": "Crême dessert"
  },
  {
    "country": "FR",
    "default": false,
    "unit": "kms",
    "active": true,
    "action": "Train",
    "source": "https://medias.sncf.com/sncfcom/pdf/DESTE/Methodologie-generale-InfoGES_2022.pdf",
    "category": "Trajets",
    "option": "Transilien",
    "amortization": 0,
    "hint": "Indiquez la distance parcourue.",
    "co2e": 7
  },
  {
    "country": "FR",
    "co2e": 63800,
    "unit": "heures",
    "comments": "gCO2e par heure",
    "active": true,
    "action": "Bateau",
    "source": "https://skeptics.stackexchange.com/questions/23050/do-jet-skis-produce-in-an-hour-equivalent-pollution-to-100-000km-of-a-new-small",
    "category": "Trajets",
    "option": "Jet skis",
    "amortization": 0,
    "hint": "Indiquez le nombre d'heures d'utilisation."
  },
  {
    "country": "FR",
    "co2e": 82200,
    "action": "Tablette",
    "active": true,
    "category": "Numérique",
    "option": "Détachable",
    "amortization": 5,
    "hint": "Indiquez le nombre de tablette détachable en votre possession. Une tablette détachable dispose d'un socle comprenant généralement un clavier."
  },
  {
    "country": "FR",
    "co2e": 85790,
    "action": "Chauffage",
    "category": "Logement",
    "option": "Bûches Poêle à bois",
    "amortization": 1,
    "hint": "Indiquez votre consommation annuelle en stères de buches.",
    "unit": "Stères",
    "active": true
  },
  {
    "country": "FR",
    "co2e": 1980,
    "action": "Lecteur musique",
    "active": true,
    "category": "Numérique",
    "option": "non tactile",
    "amortization": 10,
    "hint": "Indiquez le nombre de lecteurs de musique non tactile en votre possession."
  },
  {
    "country": "FR",
    "co2e": 296000,
    "action": "Ordinateur",
    "active": true,
    "category": "Numérique",
    "option": "Fixe haute performance",
    "amortization": 5,
    "hint": "Indiquez le nombre d'ordinateurs fixe haute performance en votre possession, disposant d'une carte graphique et CPU puissant."
  },
  {
    "co2e": 100,
    "country": "FR",
    "default": true,
    "action": "Café",
    "active": true,
    "category": "Repas",
    "option": "Expresso"
  },
  {
    "country": "FR",
    "co2e": 17,
    "default": true,
    "comments": "Mix énergétique Français",
    "active": true,
    "action": "Electricité",
    "source": "https://www.rte-france.com/eco2mix/les-emissions-de-co2-par-kwh-produit-en-france",
    "category": "Logement",
    "option": "Mix Français",
    "amortization": 1,
    "hint": "Indiquez votre consommation annuelle en kilowattheure indiquée sur votre facture annuelle d'électricité.",
    "unit": "kWh"
  },
  {
    "country": "FR",
    "unit": "kms",
    "comments": "Voiture particulière/Coeur de gamme - Véhicule compact/Hybride, full, Prius",
    "active": true,
    "action": "Voiture",
    "source": "https://base-empreinte.ademe.fr/donnees/jeu-donnees",
    "category": "Trajets",
    "option": "Hybride",
    "amortization": 0,
    "hint": "Indiquez la distance parcourue.",
    "co2e": 62
  },
  {
    "country": "FR",
    "co2e": 9430,
    "unit": "heures",
    "comments": "g co2e / heure d'utilisation",
    "active": true,
    "action": "Bateau",
    "category": "Trajets",
    "option": "Voilier à moteur",
    "amortization": 0,
    "hint": "Indiquez le nombre d'heures d'utilisation."
  },
  {
    "country": "FR",
    "co2e": 7,
    "unit": "kms",
    "active": true,
    "action": "Train",
    "source": "https://medias.sncf.com/sncfcom/pdf/DESTE/Methodologie-generale-InfoGES_2022.pdf",
    "category": "Trajets",
    "option": "THALYS",
    "amortization": 0,
    "hint": "Indiquez la distance parcourue."
  },
  {
    "country": "FR",
    "co2e": 13000,
    "default": true,
    "action": "Chemise",
    "active": true,
    "source": "https://impactco2.fr/habillement",
    "category": "Habits",
    "option": "Coton",
    "amortization": 2,
    "hint": "Indiquez le nombre de chemises en coton en votre possession."
  },
  {
    "country": "FR",
    "co2e": 1.2,
    "unit": "euros",
    "action": "Banque",
    "active": true,
    "category": "Services",
    "option": "Crédit Agricole"
  },
  {
    "country": "FR",
    "co2e": 1.04,
    "unit": "euros",
    "action": "Banque",
    "active": true,
    "category": "Services",
    "option": "BPCE"
  },
  {
    "country": "FR",
    "co2e": 1.78,
    "unit": "euros",
    "action": "Banque",
    "active": true,
    "category": "Services",
    "option": "Société générale"
  },
  {
    "country": "FR",
    "co2e": 13400,
    "action": "Chaussure",
    "active": true,
    "source": "https://impactco2.fr/habillement/chaussuresencuir",
    "category": "Habits",
    "option": "Cuir",
    "amortization": 2,
    "hint": "Indiquez le nombre de chaussures en cuir en votre possession."
  },
  {
    "co2e": 730,
    "country": "FR",
    "active": true,
    "action": "Electricité",
    "source": "https://climate.selectra.com/fr/empreinte-carbone/energie",
    "category": "Logement",
    "option": "Centrale fioul",
    "amortization": 1,
    "hint": "Indiquez votre consommation annuelle en kilowattheure indiquée sur votre facture annuelle d'électricité.",
    "unit": "kWh"
  },
  {
    "country": "FR",
    "co2e": 301000,
    "action": "Frigidaire",
    "category": "Electroménager",
    "option": "Congélateur coffre 261 L",
    "amortization": 10,
    "hint": "Indiquez le nombre de congélateurs (de type coffre), d'une capacité d'environ 261 L en votre possession."
  },
  {
    "country": "FR",
    "co2e": 24800,
    "action": "Chaise",
    "category": "Mobilier",
    "option": "Bois & Textile ",
    "amortization": 10,
    "hint": "Indiquez le nombre de chaises en bois et textile dans votre logement."
  },
  {
    "co2e": 75,
    "country": "FR",
    "default": true,
    "action": "Entrée",
    "active": true,
    "category": "Repas",
    "option": "Végétarienne"
  },
  {
    "country": "FR",
    "co2e": 6000,
    "default": true,
    "action": "T-shirt",
    "active": true,
    "category": "Habits",
    "option": "Coton",
    "amortization": 2,
    "hint": "Indiquez le nombre de T-shirts en coton en votre prossession."
  },
  {
    "country": "FR",
    "unit": "kms",
    "active": true,
    "action": "Train",
    "source": "https://medias.sncf.com/sncfcom/pdf/DESTE/Methodologie-generale-InfoGES_2022.pdf",
    "category": "Trajets",
    "option": "Tramway",
    "amortization": 0,
    "hint": "Indiquez la distance parcourue.",
    "co2e": 3
  },
  {
    "country": "FR",
    "co2e": 0.96,
    "unit": "euros",
    "action": "Banque",
    "active": true,
    "category": "Services",
    "option": "La banque postale"
  },
  {
    "country": "FR",
    "co2e": 425000,
    "action": "Immobilier",
    "category": "Logement",
    "option": "Maison ",
    "amortization": 50,
    "unit": "m2",
    "hint": "Indiquez la surface du logement construit.",
    "active": true
  },
  {
    "country": "FR",
    "co2e": 60100,
    "default": true,
    "action": "Table",
    "category": "Mobilier",
    "option": "Bois",
    "amortization": 10,
    "hint": "Indiquez le nombre de tables en bois dans votre logement."
  },
  {
    "co2e": 300,
    "country": "FR",
    "action": "Entrée",
    "active": true,
    "category": "Repas",
    "option": "Viande"
  },
  {
    "country": "FR",
    "co2e": 16500,
    "action": "Mobile",
    "active": true,
    "category": "Numérique",
    "option": "classique",
    "amortization": 5,
    "hint": "Indiquez le nombre de mobile classique en votre possession, en dehors des smartphones avec écran tactiles."
  },
  {
    "country": "FR",
    "default": true,
    "unit": "arrêts",
    "comments": "Distance is not KM but number of stations // ~0.57 Km between 2 stations (Paris) // 2.5 gCo2e / km (Paris)",
    "active": true,
    "action": "Métro",
    "category": "Trajets",
    "option": "Paris",
    "hint": "Indiquez le nombre d'arrêts.",
    "co2e": 2,
    "amortization": 0
  },
  {
    "co2e": 115,
    "country": "FR",
    "action": "Dessert",
    "active": true,
    "category": "Repas",
    "option": "Pâtisserie"
  },
  {
    "co2e": 418,
    "country": "FR",
    "active": true,
    "action": "Electricité",
    "source": "https://climate.selectra.com/fr/empreinte-carbone/energie",
    "category": "Logement",
    "option": "Centrale gaz",
    "amortization": 1,
    "hint": "Indiquez votre consommation annuelle en kilowattheure indiquée sur votre facture annuelle d'électricité.",
    "unit": "kWh"
  },
  {
    "co2e": 100,
    "country": "FR",
    "default": true,
    "action": "Boissons",
    "active": true,
    "category": "Repas",
    "option": "Eau en bouteille"
  },
  {
    "country": "FR",
    "co2e": 144000,
    "action": "Immobilier",
    "category": "Logement",
    "option": "Logement écoconçu",
    "amortization": 50,
    "unit": "m2",
    "hint": "Indiquez la surface du logement construit.",
    "active": true
  },
  {
    "co2e": 2395,
    "country": "FR",
    "action": "Principal",
    "active": true,
    "category": "Repas",
    "option": "Viande rouge"
  },
  {
    "country": "FR",
    "co2e": 5900000,
    "action": "Voiture",
    "category": "Objets",
    "option": "Hydrogène",
    "active": true,
    "hint": "Indiquez le nombre de voitures à hydrogène en votre prossession.",
    "amortization": 20
  },
  {
    "country": "FR",
    "unit": "kms",
    "active": true,
    "action": "Train",
    "source": "https://medias.sncf.com/sncfcom/pdf/DESTE/Methodologie-generale-InfoGES_2022.pdf",
    "category": "Trajets",
    "option": "TGV INOUI",
    "amortization": 0,
    "hint": "Indiquez la distance parcourue.",
    "co2e": 3
  },
  {
    "co2e": 16.8,
    "country": "FR",
    "default": true,
    "action": "Fromage",
    "active": true,
    "category": "Repas",
    "option": "Emmental"
  },
  {
    "country": "FR",
    "co2e": 305000,
    "action": "Lave-linge",
    "category": "Electroménager",
    "option": "capacité 5 kg",
    "amortization": 10,
    "hint": "Indiquez le nombre de lave-linge d'une capacité d'environ 5L en votre possession."
  },
  {
    "country": "FR",
    "co2e": 40900,
    "action": "Tablette",
    "active": true,
    "category": "Numérique",
    "option": "Mini ",
    "amortization": 5,
    "hint": "Indiquez le nombre de tablette en votre possession, de taille inférieur à 9 pouces, soit une diagonale inférieur à 23 cm."
  },
  {
    "country": "FR",
    "co2e": 169000,
    "action": "Ordinateur",
    "active": true,
    "category": "Numérique",
    "option": "Fixe bureautique",
    "amortization": 5,
    "hint": "Indiquez le nombre d'ordinateurs fixe de type destiné à la bureautique en votre possession."
  },
  {
    "co2e": 120,
    "country": "FR",
    "action": "Accompagnement",
    "active": true,
    "category": "Repas",
    "option": "Blé"
  },
  {
    "country": "FR",
    "co2e": 146,
    "unit": "kms",
    "active": true,
    "action": "Autocar",
    "source": "https://medias.sncf.com/sncfcom/pdf/DESTE/Methodologie-generale-InfoGES_2022.pdf",
    "category": "Trajets",
    "option": "Agglomération",
    "amortization": 0,
    "hint": "Indiquez la distance parcourue."
  },
  {
    "country": "FR",
    "unit": "kms",
    "active": true,
    "action": "Train",
    "source": "https://medias.sncf.com/sncfcom/pdf/DESTE/Methodologie-generale-InfoGES_2022.pdf",
    "category": "Trajets",
    "option": "OUIGO",
    "amortization": 0,
    "hint": "Indiquez la distance parcourue.",
    "co2e": 1
  },
  {
    "co2e": 22.8,
    "country": "FR",
    "action": "Fromage",
    "active": true,
    "category": "Repas",
    "option": "Cheddar"
  },
  {
    "country": "FR",
    "co2e": 195,
    "unit": "heures",
    "comments": "Transport maritime par ferry (dont flotte, utilisation et infrastructure) [tkm], GLO, ADEME",
    "active": true,
    "action": "Bateau",
    "source": "https://base-empreinte.ademe.fr/donnees/jeu-donnees",
    "category": "Trajets",
    "option": "Ferry",
    "amortization": 0,
    "hint": "Indiquez le nombre d'heures d'utilisation."
  },
  {
    "country": "FR",
    "co2e": 73700,
    "default": true,
    "action": "Console",
    "active": true,
    "category": "Numérique",
    "option": "Console de salon",
    "amortization": 5,
    "hint": "Indiquez le nombre de consoles de salon en votre possession."
  },
  {
    "co2e": 18,
    "country": "FR",
    "action": "Fromage",
    "active": true,
    "category": "Repas",
    "option": "Gorgonzola"
  },
  {
    "country": "FR",
    "co2e": 30800,
    "action": "Console",
    "active": true,
    "category": "Numérique",
    "option": "Console portable",
    "amortization": 5,
    "hint": "Indiquez le nombre de consoles portables en votre possession."
  },
  {
    "co2e": 130,
    "country": "FR",
    "action": "Principal",
    "active": true,
    "category": "Repas",
    "option": "Oeuf"
  },
  {
    "country": "FR",
    "co2e": 34.5,
    "default": true,
    "grammesPerPortion": 50,
    "hint": "Une portion de pain de 50g, correspondant à un petit pain que l'on trouve dans les cafétérias.",
    "action": "Pain",
    "active": true,
    "category": "Repas",
    "co2PerGrammes": 0.69,
    "option": "Baguette"
  },
  {
    "co2e": 16,
    "country": "FR",
    "active": true,
    "action": "Electricité",
    "source": "https://climate.selectra.com/fr/empreinte-carbone/energie",
    "category": "Logement",
    "option": "Biométhane ",
    "amortization": 1,
    "hint": "Indiquez votre consommation annuelle en kilowattheure indiquée sur votre facture annuelle d'électricité.",
    "unit": "kWh"
  },
  {
    "country": "FR",
    "default": true,
    "unit": "kms",
    "active": true,
    "action": "Autocar",
    "source": "https://medias.sncf.com/sncfcom/pdf/DESTE/Methodologie-generale-InfoGES_2022.pdf",
    "category": "Trajets",
    "option": "Autoroute",
    "amortization": 0,
    "hint": "Indiquez la distance parcourue.",
    "co2e": 30
  },
  {
    "country": "FR",
    "co2e": 82700,
    "action": "Four",
    "category": "Electroménager",
    "option": "Mini four électrique",
    "amortization": 10,
    "hint": "Indiquez le nombre de mini-four électrique en votre possession."
  },
  {
    "country": "FR",
    "co2e": 39100,
    "action": "Mobile",
    "active": true,
    "category": "Numérique",
    "option": "> 5,5 pouces",
    "amortization": 5,
    "hint": "Indiquez le nombre de mobile en votre possession, dont la taille est supérieur à 5,5 pouces."
  },
  {
    "country": "FR",
    "co2e": 314,
    "active": true,
    "action": "Electricité",
    "source": "https://climate.selectra.com/fr/empreinte-carbone/energie",
    "category": "Logement",
    "option": "Fioul domestique",
    "amortization": 1,
    "hint": "Indiquez votre consommation annuelle en kilowattheure indiquée sur votre facture annuelle d'électricité.",
    "unit": "kWh"
  },
  {
    "co2e": 950,
    "country": "FR",
    "action": "Principal",
    "active": true,
    "category": "Repas",
    "option": "Pizza"
  },
  {
    "country": "FR",
    "co2e": 4400,
    "active": true,
    "action": "Sous-vêtements",
    "category": "Habits",
    "option": "slip",
    "amortization": 2,
    "hint": "Indiquez le nombre de slips en votre prossession."
  },
  {
    "country": "FR",
    "co2e": 27600,
    "action": "Mobile",
    "active": true,
    "category": "Numérique",
    "option": "< 4,5 pouces",
    "amortization": 5,
    "hint": "Indiquez le nombre de mobile en votre possession, dont la taille est inférieur à 4,5 pouces."
  },
  {
    "country": "FR",
    "co2e": 19100,
    "action": "Chauffage",
    "category": "Logement",
    "option": "Plaquettes Poêle à bois",
    "amortization": 1,
    "unit": "MAP",
    "hint": "Un MAP est un mètre cube apparent. Indiquez votre consommation annuelle.",
    "active": true
  },
  {
    "category": "Objets",
    "country": "FR",
    "option": "Électrique",
    "co2e": 91900,
    "amortization": 5,
    "default": true,
    "active": true,
    "action": "Trottinette",
    "hint": "Indiquez le nombre de trottinettes électriques en votre prossession."
  },
  {
    "country": "FR",
    "co2e": 156000,
    "default": true,
    "action": "Ordinateur",
    "active": true,
    "category": "Numérique",
    "option": "Portable",
    "amortization": 5,
    "hint": "Indiquez le nombre d'ordinateurs portables en votre possession."
  },
  {
    "co2e": 120,
    "country": "FR",
    "default": true,
    "action": "Accompagnement",
    "active": true,
    "category": "Repas",
    "option": "Pâtes"
  },
  {
    "country": "FR",
    "co2e": 55000,
    "default": true,
    "action": "Robe",
    "active": true,
    "source": "https://impactco2.fr/habillement/robeencoton",
    "category": "Habits",
    "option": "Coton",
    "amortization": 2,
    "hint": "Indiquez le nombre de robes en coton en votre prossession."
  },
  {
    "country": "FR",
    "unit": "kms",
    "active": true,
    "action": "Train",
    "source": "https://medias.sncf.com/sncfcom/pdf/DESTE/Methodologie-generale-InfoGES_2022.pdf",
    "category": "Trajets",
    "option": "Intercités",
    "amortization": 0,
    "hint": "Indiquez la distance parcourue.",
    "co2e": 7
  },
  {
    "country": "FR",
    "co2e": 371000,
    "action": "Télévision",
    "active": true,
    "category": "Numérique",
    "option": "40-49 pouces",
    "amortization": 10,
    "hint": "Indiquez le nombre de télévisions 30-40 pouces en votre possession. Il s'agit de télévision dont la diagonale varie entre 1 mètre et 1 mètre 25 (écran de taille moyenne)."
  },
  {
    "country": "FR",
    "co2e": 961000,
    "action": "Lave-vaiselle",
    "category": "Electroménager",
    "option": "professionnel",
    "amortization": 10,
    "hint": "Indiquez le nombre de lave-vaiselle (de type professionnel) en votre possession."
  },
  {
    "co2e": 30.9,
    "country": "FR",
    "action": "Fromage",
    "active": true,
    "category": "Repas",
    "option": "Grana padano"
  },
  {
    "country": "FR",
    "co2e": 2450,
    "default": true,
    "action": "Chauffage",
    "category": "Logement",
    "option": "Granulés Poêle à bois",
    "amortization": 1,
    "hint": "Un sac standard de granulés pèse 15 Kgs. Indiquez votre consommation annuelle.",
    "unit": "Sacs",
    "active": true
  },
  {
    "country": "FR",
    "co2e": 110,
    "unit": "kms",
    "active": true,
    "action": "Bus",
    "source": "https://medias.sncf.com/sncfcom/pdf/DESTE/Methodologie-generale-InfoGES_2022.pdf",
    "category": "Trajets",
    "option": "Hors RATP",
    "amortization": 0,
    "hint": "Indiquez la distance parcourue."
  },
  {
    "country": "FR",
    "co2e": 83000,
    "action": "Aspirateur",
    "category": "Electroménager",
    "option": "Professionnel à traîneaux",
    "amortization": 10,
    "hint": "Indiquez le nombre d'aspirateurs professionnel à traîneaux en votre possession."
  },
  {
    "country": "FR",
    "co2e": 182000,
    "action": "Canapé",
    "category": "Mobilier",
    "option": "Cuir",
    "amortization": 10,
    "hint": "Indiquez le nombre de canapés en cuir dans votre logement."
  },
  {
    "country": "FR",
    "co2e": 141,
    "unit": "kms",
    "comments": "Avion passagers/Court courrier, 2018/SANS trainées, ADEME",
    "active": true,
    "action": "Avion",
    "source": "https://base-empreinte.ademe.fr/donnees/jeu-donnees",
    "category": "Trajets",
    "option": "Court courrier",
    "amortization": 0,
    "hint": "Indiquez la distance parcourue."
  },
  {
    "country": "FR",
    "co2e": 61,
    "unit": "kms",
    "default": false,
    "active": true,
    "action": "Moto",
    "source": "https://base-empreinte.ademe.fr/documentation/base-carbone?docLink=Routier2",
    "category": "Trajets",
    "option": "< 250 cm3",
    "amortization": 0,
    "hint": "Indiquez la distance parcourue."
  },
  {
    "co2e": 335000,
    "country": "FR",
    "action": "Lit",
    "active": true,
    "category": "Mobilier",
    "option": "Matelas à ressorts & Sommier en tissu",
    "amortization": 10,
    "hint": "Indiquez le nombre de lits dans votre logement, ayant un matelas à ressorts et un sommier en tissu.",
    "default": false
  },
  {
    "country": "FR",
    "co2e": 5680000,
    "action": "Voiture",
    "category": "Objets",
    "option": "Hybride",
    "active": true,
    "hint": "Indiquez le nombre de voitures hybrides en votre prossession.",
    "amortization": 20
  },
  {
    "co2e": 335,
    "country": "FR",
    "action": "Boissons",
    "active": true,
    "category": "Repas",
    "option": "Boisson chaude"
  },
  {
    "country": "FR",
    "co2e": 56000,
    "action": "Pull",
    "active": true,
    "source": "https://impactco2.fr/habillement",
    "category": "Habits",
    "option": "Laine",
    "amortization": 2,
    "hint": "Indiquez le nombre de pulls laine en votre prossession."
  },
  {
    "country": "FR",
    "co2e": 12000,
    "action": "Chemise",
    "active": true,
    "source": "https://impactco2.fr/habillement",
    "category": "Habits",
    "option": "Viscose",
    "amortization": 2,
    "hint": "Indiquez le nombre de chemises en viscose en votre prossession."
  },
  {
    "country": "FR",
    "co2e": 50000,
    "action": "Robe",
    "active": true,
    "source": "https://impactco2.fr/habillement/robeenviscose",
    "category": "Habits",
    "option": "Viscose",
    "amortization": 2,
    "hint": "Indiquez le nombre de robes en viscose en votre prossession."
  },
  {
    "co2e": 650,
    "country": "FR",
    "action": "Principal",
    "active": true,
    "category": "Repas",
    "option": "Viande blanche"
  },
  {
    "country": "FR",
    "co2e": 197000,
    "action": "Canapé",
    "category": "Mobilier",
    "option": "Convertible",
    "amortization": 10,
    "hint": "Indiquez le nombre de canapés convertibles dans votre logement."
  },
  {
    "country": "FR",
    "unit": "kms",
    "comments": "Voiture particulière/Berline/Hydrogène électrolyse mix France décentralisée",
    "active": true,
    "action": "Voiture",
    "source": "https://base-empreinte.ademe.fr/donnees/jeu-donnees",
    "category": "Trajets",
    "option": "Hydrogène",
    "amortization": 0,
    "hint": "Indiquez la distance parcourue.",
    "co2e": 19
  },
  {
    "country": "FR",
    "co2e": 257000,
    "default": true,
    "action": "Frigidaire",
    "category": "Electroménager",
    "option": "Réfrigérateur combiné",
    "amortization": 10,
    "hint": "Indiquez le nombre de frigidaires combinés en votre possession. Il s'agit des frigidaires comportant un compartiment frigidaire et un second pour la congélation."
  },
  {
    "co2e": 55,
    "country": "FR",
    "default": true,
    "action": "Principal",
    "active": true,
    "category": "Repas",
    "option": "Végétarien"
  },
  {
    "country": "FR",
    "co2e": 12000,
    "default": true,
    "action": "Pull",
    "active": true,
    "source": "https://impactco2.fr/habillement",
    "category": "Habits",
    "option": "Coton recyclé ",
    "amortization": 2,
    "hint": "Indiquez le nombre de pulls en coton recyclé en votre prossession."
  },
  {
    "co2e": 276300,
    "country": "FR",
    "action": "Lit",
    "active": true,
    "category": "Mobilier",
    "option": "Matelas à ressorts & à lattes",
    "amortization": 10,
    "hint": "Indiquez le nombre de lits dans votre logement, ayant un matelas à ressorts et un sommier à lattes."
  },
  {
    "country": "FR",
    "unit": "kms",
    "active": true,
    "action": "Avion",
    "source": "https://medias.sncf.com/sncfcom/pdf/DESTE/Methodologie-generale-InfoGES_2022.pdf",
    "category": "Trajets",
    "option": "RER",
    "amortization": 0,
    "hint": "Indiquez la distance parcourue.",
    "co2e": 6
  },
  {
    "country": "FR",
    "co2e": 1.64,
    "unit": "euros",
    "action": "Banque",
    "active": true,
    "category": "Services",
    "option": "BNP Paribas"
  },
  {
    "country": "FR",
    "co2e": 4600,
    "unit": "kms",
    "comments": "jet privé Bernard Arnault",
    "active": true,
    "action": "Avion",
    "source": "https://www.sciencesetavenir.fr/nature-environnement/climat/l-impact-ecologique-demesure-des-jets-prives_164673",
    "category": "Trajets",
    "option": "Jet privé",
    "amortization": 0,
    "hint": "Indiquez la distance parcourue."
  },
  {
    "country": "FR",
    "co2e": 865000,
    "action": "Four",
    "category": "Electroménager",
    "option": "Professionnel",
    "amortization": 10,
    "hint": "Indiquez le nombre de four (de type professionnel) en votre possession."
  },
  {
    "country": "FR",
    "co2e": 4740000,
    "default": true,
    "action": "Voiture",
    "category": "Objets",
    "option": "Thermique",
    "active": true,
    "hint": "Indiquez le nombre de voitures thermiques en votre prossession.",
    "amortization": 20
  },
  {
    "country": "FR",
    "co2e": 20,
    "unit": "kms",
    "active": true,
    "action": "Scooter",
    "source": "https://youmatter.world/fr/moto-scooter-impact-ecologique/",
    "category": "Trajets",
    "option": "Électrique",
    "amortization": 0,
    "hint": "Indiquez la distance parcourue."
  },
  {
    "country": "FR",
    "co2e": 56000,
    "action": "Robe",
    "active": true,
    "source": "https://impactco2.fr/habillement/robeenpolyester",
    "category": "Habits",
    "option": "Polyester",
    "amortization": 2,
    "hint": "Indiquez le nombre de robes en polyester en votre prossession."
  },
  {
    "co2e": 52,
    "country": "FR",
    "grammesPerPortion": 50,
    "hint": "Une portion de pain de 50g, correspondant à un petit pain que l'on trouve dans les cafétérias.",
    "active": true,
    "action": "Pain",
    "source": "https://agribalyse.ademe.fr/app/aliments/7255#Pain,_baguette_ou_boule,_aux_c%C3%A9r%C3%A9ales_et_graines,_artisanal",
    "category": "Repas",
    "co2PerGrammes": 1.04,
    "option": "Pain aux céréales, graines"
  },
  {
    "country": "FR",
    "co2e": 10020000,
    "action": "Voiture",
    "category": "Objets",
    "option": "Électrique",
    "active": true,
    "hint": "Indiquez le nombre de voitures électriques en votre prossession.",
    "amortization": 20
  },
  {
    "country": "FR",
    "co2e": 63200,
    "default": true,
    "action": "Tablette",
    "active": true,
    "category": "Numérique",
    "option": "Classique 9-11 pouces",
    "amortization": 5,
    "hint": "Indiquez le nombre de tablette en votre possession. Une tablette classique fait entre 9 et 11 pouces."
  },
  {
    "co2e": 288,
    "country": "FR",
    "action": "Dessert",
    "active": true,
    "category": "Repas",
    "option": "Yaourt"
  },
  {
    "country": "FR",
    "co2e": 103,
    "unit": "kms",
    "comments": "Avion passagers/Moyen courrier, 2018/SANS trainées, ADEME",
    "active": true,
    "action": "Avion",
    "source": "https://base-empreinte.ademe.fr/donnees/jeu-donnees",
    "category": "Trajets",
    "option": "Moyen courrier",
    "amortization": 0,
    "hint": "Indiquez la distance parcourue."
  },
  {
    "category": "Objets",
    "country": "FR",
    "action": "Vélo",
    "option": "Électrique",
    "co2e": 262000,
    "hint": "Indiquez le nombre de vélos électriques en votre prossession.",
    "active": true,
    "amortization": 10
  },
  {
    "country": "FR",
    "co2e": 17300,
    "default": true,
    "action": "Chaussure",
    "active": true,
    "source": "https://impactco2.fr/habillement/chaussuresentissu",
    "category": "Habits",
    "option": "Tissu",
    "amortization": 2,
    "hint": "Indiquez le nombre de chaussures en tissu en votre prossession."
  },
  {
    "country": "FR",
    "co2e": 235000,
    "action": "Lave-vaiselle",
    "category": "Electroménager",
    "option": "9 couverts",
    "amortization": 10,
    "hint": "Indiquez le nombre de lave-vaiselle 9 couverts en votre possession."
  },
  {
    "country": "FR",
    "co2e": 32800,
    "default": true,
    "action": "Mobile",
    "active": true,
    "category": "Numérique",
    "option": "5 pouces",
    "amortization": 5,
    "hint": "Indiquez le nombre de mobile en votre possession, dont la taille est d'environ 5 pouces."
  },
  {
    "co2e": 45.62,
    "country": "FR",
    "action": "Fromage",
    "active": true,
    "category": "Repas",
    "option": "Mozzarella"
  },
  {
    "co2e": 13.41,
    "country": "FR",
    "action": "Fromage",
    "active": true,
    "category": "Repas",
    "option": "Cream cheese allégé"
  },
  {
    "country": "FR",
    "co2e": 907000,
    "default": true,
    "action": "Armoire",
    "category": "Mobilier",
    "option": "Armoire en bois",
    "amortization": 10,
    "hint": "Indiquez le nombre d'armoires en bois dans votre logement."
  },
  {
    "country": "FR",
    "co2e": 10000,
    "action": "Chemise",
    "active": true,
    "source": "https://impactco2.fr/habillement",
    "category": "Habits",
    "option": "Polo",
    "amortization": 2,
    "hint": "Indiquez le nombre de polos en votre prossession."
  },
  {
    "country": "FR",
    "co2e": 22,
    "unit": "kms",
    "active": false,
    "action": "Vélo",
    "source": "European Cyclists’ Federation (ECF), “Quantifying CO2 savings of Cycling.” 2011.",
    "category": "Trajets",
    "option": "Électrique",
    "amortization": 0,
    "hint": "Indiquez la distance parcourue."
  },
  {
    "category": "Objets",
    "country": "FR",
    "action": "Vélo",
    "option": "Musculaire",
    "co2e": 100000,
    "hint": "Indiquez le nombre de vélos musculaires en votre prossession.",
    "active": true,
    "default": true,
    "amortization": 10
  },
  {
    "country": "FR",
    "co2e": 242000,
    "unit": "heure",
    "comments": "g co2e / heure d'utilisation",
    "active": true,
    "action": "Bateau",
    "category": "Trajets",
    "option": "Yachts ",
    "amortization": 0,
    "hint": "Indiquez le nombre d'heures d'utilisation."
  },
  {
    "country": "FR",
    "co2e": 2700,
    "active": true,
    "action": "Sous-vêtements",
    "category": "Habits",
    "option": "lingerie féminine",
    "amortization": 2,
    "hint": "Indiquez le nombre de lingeries féminine en votre prossession."
  },
  {
    "co2e": 100,
    "country": "FR",
    "default": false,
    "action": "Café",
    "active": true,
    "category": "Repas",
    "option": "Capsule"
  },
  {
    "country": "FR",
    "co2e": 52400,
    "action": "Aspirateur",
    "category": "Electroménager",
    "option": "Domestique sans sac",
    "amortization": 10,
    "hint": "Indiquez le nombre d'aspirateurs sans sac en votre possession."
  },
  {
    "country": "FR",
    "co2e": 40200,
    "default": true,
    "action": "Cadre photo",
    "active": true,
    "category": "Numérique",
    "option": "Cadre photo numérique",
    "amortization": 10,
    "hint": "Indiquez le nombre de cadres photo en votre possession."
  },
  {
    "country": "FR",
    "co2e": 26000,
    "action": "Manteau",
    "active": true,
    "source": "https://impactco2.fr/habillement/vestesimilicuir",
    "category": "Habits",
    "option": "Veste simili-cuir",
    "amortization": 3,
    "hint": "Indiquez le nombre de vestes en simili-cuir en votre prossession."
  },
  {
    "country": "FR",
    "co2e": 525000,
    "default": true,
    "action": "Immobilier",
    "category": "Logement",
    "option": "Appartement",
    "amortization": 50,
    "unit": "m2",
    "hint": "Indiquez la surface du logement construit.",
    "active": true
  },
  {
    "country": "FR",
    "co2e": 18600,
    "default": true,
    "action": "Chaise",
    "category": "Mobilier",
    "option": "Bois ",
    "amortization": 10,
    "hint": "Indiquez le nombre de chaises en bois dans votre logement."
  },
  {
    "country": "FR",
    "co2e": 3800,
    "default": true,
    "active": true,
    "action": "Sous-vêtements",
    "category": "Habits",
    "option": "boxer",
    "amortization": 2,
    "hint": "Indiquez le nombre de boxers en votre prossession."
  },
  {
    "country": "FR",
    "co2e": 80,
    "default": true,
    "unit": "kms",
    "active": true,
    "action": "Scooter",
    "source": "https://youmatter.world/fr/moto-scooter-impact-ecologique/",
    "category": "Trajets",
    "option": "Thermique",
    "amortization": 0,
    "hint": "Indiquez la distance parcourue."
  },
  {
    "co2e": 23,
    "country": "FR",
    "default": true,
    "action": "Dessert",
    "active": true,
    "category": "Repas",
    "option": "Fruits"
  },
  {
    "country": "FR",
    "co2e": 2,
    "unit": "Mo",
    "default": true,
    "action": "Stockage",
    "active": true,
    "option": "Stockage cloud",
    "category": "Services"
  },
  {
    "country": "FR",
    "co2e": 2070,
    "action": "Chauffage",
    "category": "Logement",
    "option": "Granulés chaudière",
    "amortization": 1,
    "unit": "Sacs",
    "hint": "Un sac standard de granulés pèse 15 Kgs. Indiquez votre consommation annuelle.",
    "active": true
  },
  {
    "country": "FR",
    "co2e": 340000,
    "action": "Télévision",
    "active": true,
    "category": "Numérique",
    "option": "30-40 pouces",
    "amortization": 10,
    "hint": "Indiquez le nombre de télévisions 30-40 pouces en votre possession. Il s'agit de télévision dont la diagonale est inférieur à 1 mètre (petit écran)."
  },
  {
    "co2e": 88,
    "country": "FR",
    "grammesPerPortion": 50,
    "hint": "Une portion de pain de 50g, correspondant à un petit pain que l'on trouve dans les cafétérias.",
    "active": true,
    "action": "Pain",
    "source": "https://agribalyse.ademe.fr/app/aliments/7200#Pain_de_mie,_courant",
    "category": "Repas",
    "co2PerGrammes": 1.76,
    "option": "Pain de mie"
  },
  {
    "country": "FR",
    "co2e": 47300,
    "default": true,
    "action": "Aspirateur",
    "category": "Electroménager",
    "option": "Domestique à sac",
    "amortization": 10,
    "hint": "Indiquez le nombre d'aspirateurs à sac en votre possession."
  },
  {
    "country": "FR",
    "unit": "kms",
    "active": true,
    "action": "Train",
    "source": "https://medias.sncf.com/sncfcom/pdf/DESTE/Methodologie-generale-InfoGES_2022.pdf",
    "category": "Trajets",
    "option": "LYRIA",
    "amortization": 0,
    "hint": "Indiquez la distance parcourue.",
    "co2e": 3
  },
  {
    "country": "FR",
    "co2e": 6000,
    "action": "T-shirt",
    "active": true,
    "category": "Habits",
    "option": "Polyester",
    "amortization": 2,
    "hint": "Indiquez le nombre de T-shirts en polyester en votre prossession."
  },
  {
    "co2e": 0,
    "country": "FR",
    "action": "Boissons",
    "active": true,
    "category": "Repas",
    "option": "Eau du robinet"
  },
  {
    "co2e": 270,
    "country": "FR",
    "active": true,
    "action": "Electricité",
    "source": "https://climate.selectra.com/fr/empreinte-carbone/energie",
    "category": "Logement",
    "option": "Propane",
    "amortization": 1,
    "hint": "Indiquez votre consommation annuelle en kilowattheure indiquée sur votre facture annuelle d'électricité.",
    "unit": "kWh"
  },
  {
    "co2e": 26.75,
    "country": "FR",
    "action": "Fromage",
    "active": true,
    "category": "Repas",
    "option": "Camembert"
  },
  {
    "country": "FR",
    "category": "Objets",
    "action": "Scooter",
    "option": "Thermique",
    "co2e": 500000,
    "hint": "Indiquez le nombre de scooters thermiques en votre prossession.",
    "default": true,
    "active": true,
    "amortization": 10
  },
  {
    "country": "FR",
    "co2e": 34.5,
    "grammesPerPortion": 50,
    "hint": "Une portion de pain de 50g, correspondant à un petit pain que l'on trouve dans les cafétérias.",
    "active": true,
    "action": "Pain",
    "source": "https://agribalyse.ademe.fr/app/aliments/7261#Pain_de_campagne_maison_(avec_farine_pour_machine_%C3%A0_pain)",
    "category": "Repas",
    "co2PerGrammes": 0.69,
    "option": "Pain de campagne"
  },
  {
    "country": "FR",
    "default": true,
    "unit": "kms",
    "comments": "Navette fluviale/Donnée 2009, ADEME",
    "active": true,
    "action": "Bateau",
    "source": "https://base-empreinte.ademe.fr/donnees/jeu-donnees",
    "category": "Trajets",
    "option": "Navette fluviale",
    "amortization": 0,
    "hint": "Indiquez la distance parcourue.",
    "co2e": 64
  },
  {
    "co2e": 170,
    "country": "FR",
    "action": "Boissons",
    "active": true,
    "category": "Repas",
    "option": "Soda"
  },
  {
    "country": "FR",
    "co2e": 271000,
    "default": true,
    "action": "Lave-vaiselle",
    "category": "Electroménager",
    "option": "12 couverts",
    "amortization": 10,
    "hint": "Indiquez le nombre de lave-vaiselle 12 couverts en votre possession."
  },
  {
    "country": "FR",
    "co2e": 12,
    "action": "Opérateur mobile",
    "active": true,
    "option": "Orange",
    "category": "Services"
  },
  {
    "co2e": 58,
    "country": "FR",
    "action": "Dessert",
    "active": true,
    "category": "Repas",
    "option": "Fruits transformés"
  },
  {
    "country": "FR",
    "co2e": 385000,
    "action": "Lit",
    "active": true,
    "category": "Mobilier",
    "option": "Matelas en mousse & Sommier en tissu",
    "amortization": 10,
    "hint": "Indiquez le nombre de lits dans votre logement, ayant un matelas en mousse et un sommier en tissu."
  },
  {
    "co2e": 273,
    "country": "FR",
    "active": true,
    "action": "Electricité",
    "source": "https://climate.selectra.com/fr/empreinte-carbone/energie",
    "category": "Logement",
    "option": "Butane",
    "amortization": 1,
    "hint": "Indiquez votre consommation annuelle en kilowattheure indiquée sur votre facture annuelle d'électricité.",
    "unit": "kWh"
  },
  {
    "country": "FR",
    "default": true,
    "unit": "kms",
    "comments": "Avion passagers/Long courrier, 2018/SANS trainées, ADEME",
    "active": true,
    "action": "Avion",
    "source": "https://base-empreinte.ademe.fr/donnees/jeu-donnees",
    "category": "Trajets",
    "option": "Long courrier",
    "amortization": 0,
    "hint": "Indiquez la distance parcourue.",
    "co2e": 83
  },
  {
    "country": "FR",
    "default": true,
    "unit": "kms",
    "active": true,
    "action": "Train",
    "source": "https://medias.sncf.com/sncfcom/pdf/DESTE/Methodologie-generale-InfoGES_2022.pdf",
    "category": "Trajets",
    "option": "TER",
    "amortization": 0,
    "hint": "Indiquez la distance parcourue.",
    "co2e": 27
  },
  {
    "country": "FR",
    "co2e": 7200,
    "default": true,
    "action": "Lecteur musique",
    "active": true,
    "category": "Numérique",
    "option": "tactile",
    "amortization": 10,
    "hint": "Indiquez le nombre de lecteurs de musique tactile en votre possession."
  },
  {
    "country": "FR",
    "co2e": 179000,
    "default": true,
    "action": "Canapé",
    "category": "Mobilier",
    "option": "Textile",
    "amortization": 10,
    "hint": "Indiquez le nombre de canapés en tissu dans votre logement."
  },
  {
    "country": "FR",
    "co2e": 87600,
    "action": "Frigidaire",
    "category": "Electroménager",
    "option": "Mini-bar",
    "amortization": 10,
    "hint": "Indiquez le nombre de frigidaires de type mini-bar ou cave à vin en votre possession."
  },
  {
    "country": "FR",
    "co2e": 119,
    "default": true,
    "unit": "kms",
    "comments": "Voiture moyenne/Mixte/2018",
    "active": true,
    "action": "Voiture",
    "source": "https://base-empreinte.ademe.fr/donnees/jeu-donnees",
    "category": "Trajets",
    "option": "Thermique",
    "amortization": 0,
    "hint": "Indiquez la distance parcourue."
  },
  {
    "country": "FR",
    "co2e": 23.2,
    "action": "Opérateur mobile",
    "active": true,
    "option": "Bouygues Telecom",
    "category": "Services"
  },
  {
    "country": "FR",
    "co2e": 217000,
    "default": true,
    "action": "Four",
    "category": "Electroménager",
    "option": "Electrique encastrable",
    "amortization": 10,
    "hint": "Indiquez le nombre de four encastrable en votre possession."
  },
  {
    "co2e": 150,
    "country": "FR",
    "action": "Entrée",
    "active": true,
    "category": "Repas",
    "option": "Mixte"
  },
  {
    "co2e": 25.41,
    "country": "FR",
    "action": "Fromage",
    "active": true,
    "category": "Repas",
    "option": "Gouda"
  },
  {
    "country": "FR",
    "co2e": 1.04,
    "unit": "euros",
    "default": true,
    "action": "Banque",
    "active": true,
    "category": "Services",
    "option": "Crédit mutuel"
  },
  {
    "country": "FR",
    "co2e": 342000,
    "default": true,
    "action": "Lave-linge",
    "category": "Electroménager",
    "option": "capacité 7 kg",
    "amortization": 10,
    "hint": "Indiquez le nombre de lave-linge d'une capacité d'environ 7L en votre possession."
  },
  {
    "co2e": 51,
    "country": "FR",
    "action": "Fromage",
    "active": true,
    "category": "Repas",
    "option": "Pecorino"
  },
  {
    "country": "FR",
    "co2e": 10790,
    "action": "Chauffage",
    "category": "Logement",
    "option": "Plaquettes chaudière",
    "amortization": 1,
    "unit": "MAP",
    "hint": "Un MAP est un mètre cube apparent. Indiquez votre consommation annuelle.",
    "active": true
  },
  {
    "country": "FR",
    "co2e": 6.16,
    "action": "Opérateur mobile",
    "active": true,
    "option": "SFR",
    "category": "Services"
  },
  {
    "country": "FR",
    "co2e": 59680,
    "action": "Chauffage",
    "category": "Logement",
    "option": "Bûches chaudière",
    "amortization": 1,
    "hint": "Indiquez votre consommation annuelle en stères de buches.",
    "unit": "Stères",
    "active": true
  },
  {
    "co2e": 237,
    "country": "FR",
    "action": "Boissons",
    "active": true,
    "category": "Repas",
    "option": "Soupe"
  },
  {
    "co2e": 102,
    "country": "FR",
    "action": "Accompagnement",
    "active": true,
    "category": "Repas",
    "option": "Pommes de terre"
  },
  {
    "country": "FR",
    "co2e": 21,
    "default": true,
    "unit": "kms",
    "active": false,
    "action": "Vélo",
    "source": "European Cyclists’ Federation (ECF), “Quantifying CO2 savings of Cycling.” 2011.",
    "category": "Trajets",
    "option": "Musculaire",
    "amortization": 0,
    "hint": "Indiquez la distance parcourue."
  },
  {
    "country": "FR",
    "co2e": 34400,
    "action": "Chaise",
    "category": "Mobilier",
    "option": "Plastique ",
    "amortization": 10,
    "hint": "Indiquez le nombre de chaises en plastique dans votre logement."
  },
  {
    "co2e": 120,
    "country": "FR",
    "action": "Accompagnement",
    "active": true,
    "category": "Repas",
    "option": "Riz"
  },
  {
    "co2e": 55,
    "country": "FR",
    "action": "Accompagnement",
    "active": true,
    "category": "Repas",
    "option": "Légumes"
  },
  {
    "country": "FR",
    "co2e": 415000,
    "default": false,
    "action": "Frigidaire",
    "category": "Electroménager",
    "option": "Congélateur armoire 205 L",
    "amortization": 10,
    "hint": "Indiquez le nombre de congélateurs (de type armoire), d'une capacité d'environ 205L en votre possession."
  },
  {
    "co2e": 10.2,
    "country": "FR",
    "action": "Fromage",
    "active": true,
    "category": "Repas",
    "option": "Cottage cheese"
  },
  {
    "country": "FR",
    "co2e": 133000,
    "default": true,
    "action": "Home cinéma",
    "active": true,
    "category": "Numérique",
    "option": "5.1",
    "amortization": 15,
    "hint": "Indiquez le nombre de Home cinéma 5.1 en votre possession"
  },
  {
    "country": "FR",
    "co2e": 24000,
    "default": true,
    "action": "Pantalon",
    "active": true,
    "source": "https://impactco2.fr/habillement/jeans",
    "category": "Habits",
    "option": "Jean",
    "amortization": 2,
    "hint": "Indiquez le nombre de jeans en votre prossession."
  },
  {
    "country": "FR",
    "co2e": 80200,
    "action": "Table",
    "category": "Mobilier",
    "option": "Bois massif",
    "amortization": 10,
    "hint": "Indiquez le nombre de tables en bois massif dans votre logement."
  },
  {
    "country": "FR",
    "category": "Objets",
    "action": "Scooter",
    "option": "Électrique",
    "co2e": 1000000,
    "hint": "Indiquez le nombre de scooters électriques en votre prossession.",
    "active": true,
    "amortization": 10
  },
  {
    "country": "FR",
    "co2e": 326300,
    "default": true,
    "action": "Lit",
    "active": true,
    "category": "Mobilier",
    "option": "Matelas en mousse & Sommier à lattes",
    "amortization": 10,
    "hint": "Indiquez le nombre de lits dans votre logement, ayant un matelas en mousse et un sommier à lattes."
  },
  {
    "co2e": 140,
    "country": "FR",
    "action": "Dessert",
    "active": true,
    "category": "Repas",
    "option": "Glace"
  },
  {
    "country": "FR",
    "unit": "kms",
    "comments": "Voiture particulière/Coeur de gamme - Véhicule compact/Electrique",
    "active": true,
    "action": "Voiture",
    "source": "https://base-empreinte.ademe.fr/donnees/jeu-donnees",
    "category": "Trajets",
    "option": "Électrique",
    "amortization": 0,
    "hint": "Indiquez la distance parcourue.",
    "co2e": 12
  },
  {
    "co2e": 20.76,
    "country": "FR",
    "action": "Fromage",
    "active": true,
    "category": "Repas",
    "option": "Cream cheese"
  },
  {
    "country": "FR",
    "co2e": 40000,
    "unit": "heure",
    "comments": "gco2e / heure d'utilisation",
    "active": true,
    "action": "Bateau",
    "category": "Trajets",
    "option": "Hors-bord",
    "amortization": 0,
    "hint": "Indiquez le nombre d'heures d'utilisation."
  },
  {
    "country": "FR",
    "co2e": 44,
    "active": true,
    "action": "Electricité",
    "source": "https://climate.selectra.com/fr/empreinte-carbone/energie",
    "category": "Logement",
    "option": "Photovoltaïque ",
    "amortization": 1,
    "hint": "Indiquez votre consommation annuelle en kilowattheure indiquée sur votre facture annuelle d'électricité.",
    "unit": "kWh"
  },
  {
    "co2e": 475,
    "country": "FR",
    "action": "Boissons",
    "active": true,
    "category": "Repas",
    "option": "Jus de fruit"
  },
  {
    "country": "FR",
    "co2e": 18700,
    "action": "Chaussure",
    "active": true,
    "source": "https://impactco2.fr/habillement/chaussuresdesport",
    "category": "Habits",
    "option": "Sport",
    "amortization": 2,
    "hint": "Indiquez le nombre de chaussures de sport en votre prossession."
  },
  {
    "co2e": 9.72,
    "country": "FR",
    "action": "Fromage",
    "active": true,
    "category": "Repas",
    "option": "Fromage frais"
  },
  {
    "country": "FR",
    "co2e": 98,
    "default": true,
    "unit": "kms",
    "active": true,
    "action": "Bus",
    "source": "https://medias.sncf.com/sncfcom/pdf/DESTE/Methodologie-generale-InfoGES_2022.pdf",
    "category": "Trajets",
    "option": "RATP",
    "amortization": 0,
    "hint": "Indiquez la distance parcourue."
  },
  {
    "country": "FR",
    "co2e": 167,
    "default": true,
    "unit": "kms",
    "active": true,
    "action": "Moto",
    "source": "https://base-empreinte.ademe.fr/documentation/base-carbone?docLink=Routier2",
    "category": "Trajets",
    "option": "> 250 cm3",
    "amortization": 0,
    "hint": "Indiquez la distance parcourue."
  },
  {
    "country": "FR",
    "co2e": 14,
    "active": true,
    "action": "Electricité",
    "source": "https://climate.selectra.com/fr/empreinte-carbone/energie",
    "category": "Logement",
    "option": "Éolienne (terre)",
    "amortization": 1,
    "hint": "Indiquez votre consommation annuelle en kilowattheure indiquée sur votre facture annuelle d'électricité.",
    "unit": "kWh"
  },
  {
    "country": "FR",
    "co2e": 15,
    "active": true,
    "action": "Electricité",
    "source": "https://climate.selectra.com/fr/empreinte-carbone/energie",
    "category": "Logement",
    "option": "Éolienne (mer)",
    "amortization": 1,
    "hint": "Indiquez votre consommation annuelle en kilowattheure indiquée sur votre facture annuelle d'électricité.",
    "unit": "kWh"
  },
  {
    "country": "FR",
    "co2e": 965,
    "action": "Gaz",
    "category": "Logement",
    "option": "Gaz de haut fourneau",
    "amortization": 1,
    "hint": "Indiquez votre consommation annuelle en kilowattheure indiquée sur votre facture annuelle de gaz.",
    "unit": "kWh",
    "active": true
  },
  {
    "country": "FR",
    "co2e": 216,
    "default": true,
    "action": "Gaz",
    "category": "Logement",
    "option": "Gaz naturel",
    "amortization": 1,
    "hint": "Indiquez votre consommation annuelle en kilowattheure indiquée sur votre facture annuelle de gaz.",
    "unit": "kWh",
    "active": true
  },
  {
    "co2e": 171,
    "country": "FR",
    "action": "Gaz",
    "category": "Logement",
    "option": "Gaz de cokerie",
    "amortization": 1,
    "hint": "Indiquez votre consommation annuelle en kilowattheure indiquée sur votre facture annuelle de gaz.",
    "unit": "kWh",
    "active": true
  },
  {
    "co2e": 6,
    "country": "FR",
    "default": false,
    "active": true,
    "action": "Electricité",
    "source": "https://climate.selectra.com/fr/empreinte-carbone/energie",
    "category": "Logement",
    "option": "Nucléaire",
    "amortization": 1,
    "hint": "Indiquez votre consommation annuelle en kilowattheure indiquée sur votre facture annuelle d'électricité.",
    "unit": "kWh"
  },
  {
    "country": "FR",
    "co2e": 6,
    "active": true,
    "action": "Electricité",
    "source": "https://climate.selectra.com/fr/empreinte-carbone/energie",
    "category": "Logement",
    "option": "Hydroélectrique",
    "amortization": 1,
    "hint": "Indiquez votre consommation annuelle en kilowattheure indiquée sur votre facture annuelle d'électricité.",
    "unit": "kWh"
  },
  {
    "country": "FR",
    "co2e": 1060,
    "active": true,
    "action": "Electricité",
    "source": "https://climate.selectra.com/fr/empreinte-carbone/energie",
    "category": "Logement",
    "option": "Centrale charbon",
    "amortization": 1,
    "hint": "Indiquez votre consommation annuelle en kilowattheure indiquée sur votre facture annuelle d'électricité.",
    "unit": "kWh"
  },
  {
    "country": "FR",
    "co2e": 132,
    "default": true,
    "active": true,
    "action": "Eau",
    "category": "Logement",
    "option": "Réseau d’eau potable",
    "amortization": 1,
    "unit": "m3",
    "hint": "Indiquez votre consommation annuelle en mètres cube indiquée sur votre facture annuelle d'eau."
  },
  {
    "country": "FR",
    "co2e": 45,
    "default": false,
    "active": true,
    "action": "Electricité",
    "source": "https://climate.selectra.com/fr/empreinte-carbone/energie",
    "category": "Logement",
    "option": "Géothermique",
    "amortization": 1,
    "hint": "Indiquez votre consommation annuelle en kilowattheure indiquée sur votre facture annuelle d'électricité.",
    "unit": "kWh"
  },
  {
    "country": "FR",
    "unit": "kms",
    "active": true,
    "action": "Train",
    "source": "https://medias.sncf.com/sncfcom/pdf/DESTE/Methodologie-generale-InfoGES_2022.pdf",
    "category": "Trajets",
    "option": "Eurostar",
    "amortization": 0,
    "hint": "Indiquez la distance parcourue.",
    "co2e": 7
  },
  {
    "country": "FR",
    "co2e": 120,
    "action": "Café",
    "active": true,
    "category": "Repas",
    "option": "Café filtre"
  }
]